QRCraft/__init__.py
QRCraft/qr.py
QRCraft-0.2.dist-info/LICENSE
QRCraft-0.2.dist-info/METADATA
QRCraft-0.2.dist-info/WHEEL
QRCraft-0.2.dist-info/top_level.txt
QRCraft-0.2.dist-info/RECORD
